setup.cfg
setup.py
ChatterLearning.egg-info/PKG-INFO
ChatterLearning.egg-info/SOURCES.txt
ChatterLearning.egg-info/dependency_links.txt
ChatterLearning.egg-info/requires.txt
ChatterLearning.egg-info/top_level.txt
chatter_learning/__init__.py
chatter_learning/chatter.py
chatter_learning/exceptions.py
chatter_learning/main.py
chatter_learning/brains/__init__.py
chatter_learning/brains/base_brain.py
chatter_learning/brains/closest_mean.py
chatter_learning/brains/dict.txt.big
chatter_learning/brains/pick_strategy.py
chatter_learning/store_adapters/__init__.py
chatter_learning/store_adapters/base_store.py
chatter_learning/store_adapters/mongodb.py
examples/__init__.py
examples/demo.py
tests/__init__.py
tests/brains_tests/__init__.py
tests/brains_tests/test_closest_mean.py
tests/store_adapters_tests/__init__.py
tests/store_adapters_tests/test_mongodb.py