Metadata-Version: 1.1
Name: ChatterLearning
Version: 1.0.8
Summary: Automatic Chat
Home-page: https://github.com/gcaaa31928/ChatterLearningt
Author: GCA
Author-email: gcaaa31928@gmail.com
License: UNKNOWN
Download-URL: https://github.com/gcaaa31928/ChatterLearning/releases/tag/v1.0
Keywords: ai,chat,bot
Platform: UNKNOWN
